armetrics/__init__.py
armetrics/models.py
armetrics/plotter.py
armetrics/scorer.py
armetrics/utils.py
armetrics-0.1.14.dist-info/METADATA
armetrics-0.1.14.dist-info/WHEEL
armetrics-0.1.14.dist-info/top_level.txt
armetrics-0.1.14.dist-info/RECORD
