Metadata-Version: 2.1
Name: armetrics
Version: 0.1.14
Summary: Continuous Activity Recognition Metrics based on (Ward et al, 2011)
Home-page: http://github.com/srvanrell/armetrics
Author: srvanrell
Author-email: srvanrell@gmail.com
License: MIT
Platform: UNKNOWN
Classifier: Programming Language :: Python :: 3
Classifier: License :: OSI Approved :: MIT License
Requires-Python: >=3.5
Requires-Dist: matplotlib (>=3.0.2)
Requires-Dist: numpy (>=1.13.1)
Requires-Dist: pandas (>=0.20.1)
